brlib/__init__.py
brlib/all_major_leaguers.py
brlib/find_asg.py
brlib/find_games.py
brlib/find_teams.py
brlib/game.py
brlib/games.py
brlib/get_games.py
brlib/get_players.py
brlib/get_teams.py
brlib/options.py
brlib/player.py
brlib/players.py
brlib/team.py
brlib/teams.py
brlib/_helpers/__init__.py
brlib/_helpers/abbreviations_manager.py
brlib/_helpers/constants.py
brlib/_helpers/inputs.py
brlib/_helpers/no_hitter_dicts.py
brlib/_helpers/requests_manager.py
brlib/_helpers/singleton.py
brlib/_helpers/utils.py
brlib-0.0.2.dist-info/METADATA
brlib-0.0.2.dist-info/WHEEL
brlib-0.0.2.dist-info/licenses/LICENSE.txt
brlib-0.0.2.dist-info/RECORD
