Metadata-Version: 2.4
Name: brlib
Version: 0.0.2
Summary: A library for collecting baseball statistics from Baseball Reference
Project-URL: Homepage, https://github.com/john-bieren/brlib
Project-URL: Documentation, https://github.com/john-bieren/brlib/tree/master/docs
Project-URL: Repository, https://github.com/john-bieren/brlib.git
Project-URL: Issues, https://github.com/john-bieren/brlib/issues
Author-email: John Bieren <jbieren64@gmail.com>
License-Expression: MIT
License-File: LICENSE.txt
Keywords: baseball,baseball reference,baseball stats,mlb
Classifier: Development Status :: 4 - Beta
Classifier: Intended Audience :: Developers
Classifier: Operating System :: OS Independent
Classifier: Programming Language :: Python
Classifier: Programming Language :: Python :: 3
Classifier: Programming Language :: Python :: 3.12
Classifier: Programming Language :: Python :: 3.13
Classifier: Programming Language :: Python :: 3.14
Classifier: Topic :: Software Development :: Libraries :: Python Modules
Requires-Python: >=3.12
Requires-Dist: beautifulsoup4<5.0.0,>=4.14.0
Requires-Dist: curl-cffi<1.0.0,>=0.13.0
Requires-Dist: lxml<7.0.0,>=6.0.2
Requires-Dist: pandas<3.0.0,>=2.3.0
Requires-Dist: platformdirs<5.0.0,>=4.5.0
Requires-Dist: tqdm<5.0.0,>=4.67.1
Provides-Extra: dev
Requires-Dist: pytest>=9.0.0; extra == 'dev'
